LICENSE
eng_econ/__init__.py
eng_econ/factors.py
eng_econ-0.1.3.dist-info/LICENSE
eng_econ-0.1.3.dist-info/WHEEL
eng_econ-0.1.3.dist-info/METADATA
eng_econ-0.1.3.dist-info/RECORD
