Metadata-Version: 2.1
Name: eng-econ
Version: 0.1.3
Summary: This package provides some of the basic functions of engineering economics
Home-page: https://songyu-wang.github.io/engineering-economics-basics/
License: MIT
Keywords: engineering,economics,economy,investments
Author: Songyu-Wang
Author-email: wangsongyuf@gmail.com
Requires-Python: >=3.6,<4.0
Classifier: License :: OSI Approved :: MIT License
Classifier: Operating System :: OS Independent
Classifier: Programming Language :: Python :: 3
Classifier: Programming Language :: Python :: 3.6
Classifier: Programming Language :: Python :: 3.7
Classifier: Programming Language :: Python :: 3.8
Classifier: Topic :: Office/Business :: Financial
Project-URL: Repository, https://github.com/Songyu-Wang/engineering-economics-basics
